CHANGELOG.txt
MANIFEST.in
README.rst
requirements.txt
setup.cfg
setup.py
mlmnemonist/__init__.py
mlmnemonist/experiment_runner.py
mlmnemonist/factory.py
mlmnemonist/processing_pipeline.py
mlmnemonist/runner_cache.py
mlmnemonist.egg-info/PKG-INFO
mlmnemonist.egg-info/SOURCES.txt
mlmnemonist.egg-info/dependency_links.txt
mlmnemonist.egg-info/requires.txt
mlmnemonist.egg-info/top_level.txt
mlmnemonist/validation_tools/__init__.py
mlmnemonist/validation_tools/cfg_utils.py
mlmnemonist/validation_tools/grid_search.py
mlmnemonist/validation_tools/hyper_experiment_runner.py
mlmnemonist/validation_tools/utils.py
testing/unittest.py
testing/unittest2.py
testing/unittest3.py
testing/unittest4.py
testing/unittest5.py
testing/config/config.py
testing/config/config_drug.py
testing/mnemonic-experiments/2022-07-02-exp-0/DESCRIPTION.txt
testing/mnemonic-experiments/2022-07-02-exp-0/readme.txt
testing/mnemonic-experiments/2022-07-19-fullsearch-runner-0/DESCRIPTION.txt
testing/mnemonic-experiments/2022-07-19-fullsearch-runner-1/DESCRIPTION.txt
testing/mnemonic-experiments/2022-07-19-fullsearch-runner-2/DESCRIPTION.txt
testing/mnemonic-experiments/2022-07-19-fullsearch-runner-2/readme.txt
testing/mnemonic-experiments/2022-07-19-fullsearch-runner-3/DESCRIPTION.txt
testing/mnemonic-experiments/2022-07-19-fullsearch-runner-3/readme.txt
testing/mnemonic-experiments/2022-07-19-my-cv-fold-0/DESCRIPTION.txt
testing/mnemonic-experiments/2022-07-19-my-cv-fold-1/DESCRIPTION.txt
testing/mnemonic-experiments/2022-07-19-my-cv-fold-2/DESCRIPTION.txt
testing/mnemonic-experiments/2022-11-19-fullsearch-runner/DESCRIPTION.txt
testing/mnemonic-experiments/2022-11-19-tut1/DESCRIPTION.txt
testing/mnemonic-experiments/2022-11-20-cross-run/DESCRIPTION.txt
testing/mnemonic-experiments/2022-11-20-fullsearch-runner/DESCRIPTION.txt
testing/mnemonic-experiments/2022-11-20-regress-houses/DESCRIPTION.txt
testing/mnemonic-experiments/2022-11-20-regress-houses/readme.txt
testing/mnemonic-experiments/2022-11-20-tut-with-config/DESCRIPTION.txt
testing/mnemonic-experiments/2022-11-20-tut1/DESCRIPTION.txt
testing/mnemonic-hyper-experiments/2022-11-20-cross-run/DESCRIPTION.txt
venv/lib/python3.8/site-packages/autopep8-2.0.0.dist-info/entry_points.txt
venv/lib/python3.8/site-packages/autopep8-2.0.0.dist-info/top_level.txt
venv/lib/python3.8/site-packages/build-0.8.0.dist-info/entry_points.txt
venv/lib/python3.8/site-packages/build-0.8.0.dist-info/top_level.txt
venv/lib/python3.8/site-packages/cachetools-4.2.4.dist-info/top_level.txt
venv/lib/python3.8/site-packages/drive-0.3.2.dist-info/top_level.txt
venv/lib/python3.8/site-packages/et_xmlfile-1.1.0.dist-info/AUTHORS.txt
venv/lib/python3.8/site-packages/et_xmlfile-1.1.0.dist-info/top_level.txt
venv/lib/python3.8/site-packages/google_api_core-1.31.6.dist-info/namespace_packages.txt
venv/lib/python3.8/site-packages/google_api_core-1.31.6.dist-info/top_level.txt
venv/lib/python3.8/site-packages/google_api_python_client-2.7.0.dist-info/top_level.txt
venv/lib/python3.8/site-packages/google_auth-1.35.0.dist-info/namespace_packages.txt
venv/lib/python3.8/site-packages/google_auth-1.35.0.dist-info/top_level.txt
venv/lib/python3.8/site-packages/google_auth_httplib2-0.1.0.dist-info/top_level.txt
venv/lib/python3.8/site-packages/googleapis_common_protos-1.56.3.dist-info/namespace_packages.txt
venv/lib/python3.8/site-packages/googleapis_common_protos-1.56.3.dist-info/top_level.txt
venv/lib/python3.8/site-packages/httplib2-0.19.1.dist-info/top_level.txt
venv/lib/python3.8/site-packages/oauth2client-4.1.3.dist-info/top_level.txt
venv/lib/python3.8/site-packages/openpyxl-3.0.7.dist-info/top_level.txt
venv/lib/python3.8/site-packages/pip-22.1.2.dist-info/LICENSE.txt
venv/lib/python3.8/site-packages/pip-22.1.2.dist-info/entry_points.txt
venv/lib/python3.8/site-packages/pip-22.1.2.dist-info/top_level.txt
venv/lib/python3.8/site-packages/pycodestyle-2.9.1.dist-info/entry_points.txt
venv/lib/python3.8/site-packages/pycodestyle-2.9.1.dist-info/top_level.txt
venv/lib/python3.8/site-packages/python_magic-0.4.27.dist-info/top_level.txt
venv/lib/python3.8/site-packages/setuptools-57.0.0.dist-info/dependency_links.txt
venv/lib/python3.8/site-packages/setuptools-57.0.0.dist-info/entry_points.txt
venv/lib/python3.8/site-packages/setuptools-57.0.0.dist-info/top_level.txt
venv/lib/python3.8/site-packages/uritemplate-3.0.1.dist-info/top_level.txt
venv/lib/python3.8/site-packages/wheel-0.36.2.dist-info/LICENSE.txt
venv/lib/python3.8/site-packages/wheel-0.36.2.dist-info/entry_points.txt
venv/lib/python3.8/site-packages/wheel-0.36.2.dist-info/top_level.txt
